mstar/__init__.py
mstar/_modidx.py
mstar/core.py
mstar-0.0.4.dist-info/LICENSE
mstar-0.0.4.dist-info/METADATA
mstar-0.0.4.dist-info/WHEEL
mstar-0.0.4.dist-info/entry_points.txt
mstar-0.0.4.dist-info/top_level.txt
mstar-0.0.4.dist-info/RECORD
