Metadata-Version: 2.1
Name: mstar
Version: 0.0.4
Summary: mstar
Home-page: https://github.com/dsm-72/mstar
Author: dsm-72
Author-email: sumner.magruder@yale.edu
License: Apache Software License 2.0
Keywords: mstar star mod ast asterick
Classifier: Development Status :: 4 - Beta
Classifier: Intended Audience :: Developers
Classifier: Natural Language :: English
Classifier: Programming Language :: Python :: 3.11
Classifier: License :: OSI Approved :: Apache Software License
Requires-Python: >=3.11
License-File: LICENSE
Requires-Dist: atyp
Requires-Dist: nchr
Requires-Dist: nlit
Requires-Dist: chck
Requires-Dist: idfunc
Requires-Dist: atup
Provides-Extra: dev
